mapfost/__init__.py
mapfost/costDerivativesLib.py
mapfost/costLib.py
mapfost/imageLib.py
mapfost/mapfost.py
mapfost/mapfost_hess_lib.py
mapfost/mtfLib.py
mapfost-4.3.1.dist-info/LICENSE
mapfost-4.3.1.dist-info/METADATA
mapfost-4.3.1.dist-info/WHEEL
mapfost-4.3.1.dist-info/top_level.txt
mapfost-4.3.1.dist-info/RECORD
