Metadata-Version: 2.1
Name: mapfost
Version: 4.3.1
Summary: Implementation of the autofocus method MAPFoSt. Publication: Binding J, Mikula S, Denk W. Low-dosage Maximum-A-Posteriori Focusing and Stigmation. Microsc Microanal. 2013
Home-page: https://github.com/pypa/mapfost
Author: Rangoli Saxena
Author-email: rangolisaxena90@gmail.com
License: MIT
Project-URL: Bug Tracker, https://github.com/pypa/mapfost/issues
Platform: UNKNOWN
Classifier: Programming Language :: Python :: 3
Classifier: License :: OSI Approved :: MIT License
Classifier: Operating System :: OS Independent
Requires-Python: >=3.6
License-File: LICENSE
